{
  "todos": [
    {
      "title": "Enim facilisis gravida neque convallis a cras semper auctor neque.",
      "description": "Eu lobortis elementum nibh tellus molestie nunc., At augue eget arcu dictum varius duis at consectetur.",
      "compeleted": false,
      "id": 10
    },
    {
      "title": "Scelerisque viverra mauris in aliquam.",
      "description": "Leo in vitae turpis massa sed elementum tempus egestas., A diam sollicitudin tempor id eu nisl nunc.",
      "compeleted": false,
      "id": 12
    },
    {
      "title": "Ornare arcu odio ut sem.",
      "description": "Semper auctor neque vitae tempus., Vel facilisis volutpat est velit egestas dui id ornare arcu.",
      "compeleted": false,
      "id": 14
    },
    {
      "title": "Egestas purus viverra accumsan in nisl nisi scelerisque eu ultrices.",
      "description": "Scelerisque purus semper eget duis., Diam vel quam elementum pulvinar etiam non.",
      "compeleted": false,
      "id": 15
    },
    {
      "title": "Turpis tincidunt id aliquet risus feugiat.",
      "description": "Dolor sit amet consectetur adipiscing elit pellentesque habitant., Netus et malesuada fames ac turpis egestas maecenas pharetra convallis.",
      "compeleted": false,
      "id": 16
    },
    {
      "title": "Tristique senectus et netus et malesuada fames ac turpis egestas.",
      "description": "Amet porttitor eget dolor morbi non arcu risus quis., Porttitor eget dolor morbi non arcu risus quis varius quam.",
      "compeleted": false,
      "id": 17
    }
  ],
  "users": []
}